sciapiary/__init__.py
sciapiary-0.0.0.dist-info/licenses/LICENSE
sciapiary-0.0.0.dist-info/METADATA
sciapiary-0.0.0.dist-info/WHEEL
sciapiary-0.0.0.dist-info/top_level.txt
sciapiary-0.0.0.dist-info/RECORD
